dcbase
