Metadata-Version: 1.1
Name: dc-django-base
Version: 0.6.3
Summary: Django base application
Home-page: https://github.com/tctimmeh/dc-django-base
Author: Tim Court
Author-email: tctimmeh@gmail.com
License: MIT License
Platform: UNKNOWN
Classifier: Development Status :: 4 - Beta
Classifier: Environment :: Web Environment
Classifier: Framework :: Django
Classifier: Intended Audience :: Developers
Classifier: License :: OSI Approved :: MIT License
Classifier: Operating System :: OS Independent
Classifier: Programming Language :: Python
Classifier: Programming Language :: Python :: 3
Classifier: Programming Language :: Python :: 3.4
